transmogrify/__init__.py
transmogrify/core.py
transmogrify/create_doc_imgs.py
transmogrify/geometry.py
transmogrify/images2gif.py
transmogrify/network.py
transmogrify/optimize.py
transmogrify/processors.py
transmogrify/settings.py
transmogrify/utils.py
transmogrify/wsgi.py
transmogrify/autodetect/__init__.py
transmogrify/filesystem/__init__.py
transmogrify/filesystem/s3.py
transmogrify/filters/__init__.py
transmogrify/tests/__init__.py
transmogrify/tests/autodetect.py
transmogrify/tests/facedetect.py
transmogrify/tests/test_base.py
transmogrify/tests/test_optimize.py
transmogrify/tests/test_utils.py
transmogrify-2.0.6.data/scripts/configure_transmogrify
transmogrify-2.0.6.dist-info/DESCRIPTION.rst
transmogrify-2.0.6.dist-info/METADATA
transmogrify-2.0.6.dist-info/RECORD
transmogrify-2.0.6.dist-info/WHEEL
transmogrify-2.0.6.dist-info/metadata.json
transmogrify-2.0.6.dist-info/top_level.txt
