Metadata-Version: 2.0
Name: transmogrify
Version: 2.0.6
Summary: Allows for the dynamic alteration of images using the URL.
Home-page: http://github.com/callowayproject/Transmogrify/
Author: Corey Oordt
Author-email: coreyoordt@gmail.com
License: UNKNOWN
Platform: UNKNOWN
Classifier: Development Status :: 4 - Beta
Classifier: License :: OSI Approved :: Apache Software License
Classifier: Programming Language :: Python :: 2
Requires-Dist: Pillow
Requires-Dist: daiquiri
Requires-Dist: gunicorn
Requires-Dist: numpy
Requires-Dist: opencv-python
Requires-Dist: wsgiref
